[
  {
    "id": "mo1qt0hu",
    "ts": "2026-04-16T17:17:56.034Z",
    "name": "zouhir",
    "email": "charifi.idrissi.zouhir@gmail.com",
    "message": "test test test",
    "budget": "< 500€",
    "read": true
  },
  {
    "id": "mo1qyquw",
    "ts": "2026-04-16T17:22:23.480Z",
    "name": "zouhir echarif el idrissi el kandri",
    "email": "charifi.idrissi.zouhir@gmail.com",
    "message": "ldjfs dfs dflqsdf qlsd;",
    "budget": "500–1 500€",
    "read": true
  },
  {
    "id": "mo1r3wyf",
    "ts": "2026-04-16T17:26:24.663Z",
    "name": "Zouhir Echarif el idrissi el kandri",
    "email": "charifi.idrissi.zouhir@gmail.com",
    "message": "jhs diqs dqposd qsdq;s",
    "budget": "500–1 500€",
    "read": true
  },
  {
    "id": "mo1rdt89",
    "ts": "2026-04-16T17:34:06.393Z",
    "name": "zouhir echarif el idrissi el kandri",
    "email": "charifi.idrissi.zouhir@gmail.com",
    "message": "ldjfs dfs dflqsdf qlsd;",
    "budget": "500–1 500€",
    "read": true
  },
  {
    "id": "mo1re4i9",
    "ts": "2026-04-16T17:34:21.009Z",
    "name": "zouhir echarif el idrissi el kandri",
    "email": "charifi.idrissi.zouhir@gmail.com",
    "message": "jjjjjjjjjjjjjjjjjjjjjjjjjjjjjj",
    "budget": "500–1 500€",
    "read": true
  }
]